{
  "main": {
    "id": "5324373015726ba8",
    "type": "split",
    "children": [
      {
        "id": "0bbefb67a4ca5300",
        "type": "tabs",
        "children": [
          {
            "id": "6e2847a62cf5ccc9",
            "type": "leaf",
            "state": {
              "type": "empty",
              "state": {},
              "icon": "lucide-file",
              "title": "New tab"
            }
          }
        ]
      }
    ],
    "direction": "vertical"
  },
  "left": {
    "id": "1d37cfb64de465e5",
    "type": "split",
    "children": [
      {
        "id": "d920f33dfe96dc72",
        "type": "tabs",
        "dimension": 71.20370370370371,
        "children": [
          {
            "id": "77e881ccac936092",
            "type": "leaf",
            "state": {
              "type": "outline",
              "state": {
                "followCursor": false,
                "showSearch": false,
                "searchQuery": ""
              },
              "icon": "lucide-list",
              "title": "Outline"
            }
          }
        ]
      },
      {
        "id": "bedf647ec6464905",
        "type": "tabs",
        "dimension": 28.796296296296294,
        "children": [
          {
            "id": "9b2972a896ec0f84",
            "type": "leaf",
            "state": {
              "type": "backlink",
              "state": {
                "collapseAll": false,
                "extraContext": false,
                "sortOrder": "alphabetical",
                "showSearch": false,
                "searchQuery": "",
                "backlinkCollapsed": false,
                "unlinkedCollapsed": false
              },
              "icon": "links-coming-in",
              "title": "Backlinks"
            }
          }
        ]
      }
    ],
    "direction": "horizontal",
    "width": 283.5
  },
  "right": {
    "id": "52365d8cf2e0fd6b",
    "type": "split",
    "children": [
      {
        "id": "7868a9ec39c25203",
        "type": "tabs",
        "children": [
          {
            "id": "b0d6ac92bcf66e4b",
            "type": "leaf",
            "state": {
              "type": "file-explorer",
              "state": {
                "sortOrder": "alphabetical",
                "autoReveal": false
              },
              "icon": "lucide-folder-closed",
              "title": "Files"
            }
          },
          {
            "id": "4306dcf7651c10de",
            "type": "leaf",
            "state": {
              "type": "search",
              "state": {
                "query": "tag:#typescript  ",
                "matchingCase": false,
                "explainSearch": false,
                "collapseAll": false,
                "extraContext": false,
                "sortOrder": "alphabetical"
              },
              "icon": "lucide-search",
              "title": "Search"
            }
          }
        ]
      }
    ],
    "direction": "horizontal",
    "width": 365
  },
  "left-ribbon": {
    "hiddenItems": {
      "switcher:Open quick switcher": true,
      "graph:Open graph view": true,
      "command-palette:Open command palette": true,
      "templater-obsidian:Templater": true,
      "obsidian-day-and-night:Toggle Theme": false
    }
  },
  "active": "6e2847a62cf5ccc9",
  "lastOpenFiles": [
    "dump/concepts/functional_programming/functional_programming_pure_functions.md",
    "dump/concepts/functional_programming/functional_programming_lambda.md",
    "dump/concepts/functional_programming/concepts_functional_programming.md",
    "dump/concepts/functional_programming/functional_programming_immutability.md",
    "dump/concepts/concepts_programming_paradigms.md",
    "dump/concepts/functional_programming",
    "dump/concepts/functional_programming.md",
    "dump/concepts/oop/concepts_oop.md",
    "dump/concepts/oop/oop_abstraction.md",
    "dump/concepts/oop_solid.md",
    "dump/concepts/oop/oop_encapsulation.md",
    "dump/concepts/concepts.md",
    "dump/concepts/concepts_design_patterns.md",
    "dump/concepts/concepts_webdevconcepts.md",
    "oop.md",
    "oop_encapsulation.md",
    "dump/concepts/oop",
    "dump/_indexes/programming.md",
    "formats_dataExchange.md",
    "dump/json.md",
    "dump/_indexes/webdev.md",
    "dump/_indexes/webdesign.md",
    "dump/css/CSS.md",
    "dump/bootstrap/bootstrap.md",
    "dump/concepts/concepts_responsive_design.md",
    "dump/html/html_DOM.md",
    "dump/concepts/dom.md",
    "dump/_indexes/nexus.md",
    "dump/linux/proxmox",
    "Untitled",
    "Assets/{52FA080D-F610-4443-BF1E-F5808B1CFCF3}.png",
    "Assets/Pasted image 20240911193149.png",
    "Assets/Pasted image 20240212182305.png",
    "dump/linux/wayland",
    "dump/linux/wayland/hyprland",
    "dump/linux/yazi",
    "Assets/zVPJ6v2bRB-Tyer9m1Qf5A_33700a0849b040bf8f8afefe2a38ebe1_BED_C2M2L1_item04-img01.png",
    "dump/git",
    "dump/config",
    "dump/obsidian",
    "Assets/{D2195147-892A-4344-A8C0-1966D6FC7AAE}.png",
    "Assets/{E10EF46D-0EF3-4300-ADE1-B23719867B1A}.png",
    "Assets/372081412-349c5bb6-903c-422e-be19-63db2f66ff77.png",
    "Assets/376050291-513b4bff-698b-4a89-bcda-b5dffeade3eb.png",
    "Assets/Screenshot-from-2023-10-21-15-16-36.png",
    "Assets/Pasted image 20250215213929.png",
    "Untitled 2.canvas",
    "Untitled 1.canvas",
    "Untitled.canvas"
  ]
}