{
  "anuppuccin-theme-settings@@anuppuccin-theme-light": "ctp-latte",
  "anuppuccin-theme-settings@@anuppuccin-theme-dark": "ctp-macchiato",
  "anuppuccin-theme-settings@@anuppuccin-light-theme-accents": "ctp-accent-light-sapphire",
  "anuppuccin-theme-settings@@anuppuccin-accent-toggle": true,
  "anuppuccin-theme-settings@@anp-active-line": "anp-current-line-border-only",
  "anuppuccin-theme-settings@@anp-autohide-titlebar": false,
  "anuppuccin-theme-settings@@anp-cursor": "pointer",
  "anuppuccin-theme-settings@@anp-toggle-metadata": false,
  "anuppuccin-theme-settings@@anp-toggle-scrollbars": false,
  "anuppuccin-theme-settings@@anp-hide-status-bar": false,
  "anuppuccin-theme-settings@@anp-hide-external-link-icon": true,
  "anuppuccin-theme-settings@@anp-header-color-toggle": true,
  "anuppuccin-theme-settings@@anp-header-divider-color-toggle": true,
  "anuppuccin-theme-settings@@anp-h1-divider": true,
  "anuppuccin-theme-settings@@anp-h1-color-custom": "none",
  "anuppuccin-theme-settings@@anp-colorful-frame-opacity": 0.25,
  "anuppuccin-theme-settings@@anp-colorful-frame": false,
  "anuppuccin-theme-settings@@anp-colorful-frame-color@@light": "#FF0000",
  "anuppuccin-theme-settings@@anp-alt-rainbow-style": "anp-default-rainbow",
  "anuppuccin-theme-settings@@anp-simple-rainbow-title-toggle": true,
  "anuppuccin-theme-settings@@anp-simple-rainbow-collapse-icon-toggle": true,
  "anuppuccin-theme-settings@@anp-simple-rainbow-indentation-toggle": true,
  "anuppuccin-theme-settings@@anp-simple-rainbow-icon-toggle": false,
  "anuppuccin-theme-settings@@anp-rainbow-subfolder-color-toggle": true,
  "anuppuccin-theme-settings@@anp-status-bar-select": "none",
  "anuppuccin-theme-settings@@anp-alt-tab-style": "anp-safari-tab-toggle",
  "anuppuccin-theme-settings@@anp-layout-select": "anp-card-layout",
  "anuppuccin-theme-settings@@anp-card-shadows": false,
  "anuppuccin-theme-settings@@anp-card-layout-actions": false,
  "anuppuccin-theme-settings@@anp-hide-borders": true,
  "anuppuccin-theme-settings@@anp-bg-fix": false,
  "anuppuccin-theme-settings@@anp-safari-tab-animated": false,
  "anuppuccin-theme-settings@@anp-h2-color-custom": "anp-h2-flamingo",
  "anuppuccin-theme-settings@@anp-h2-divider": true,
  "anuppuccin-theme-settings@@anp-h3-color-custom": "anp-h3-green"
}